fhdw/modelling/__init__.py
fhdw/modelling/base.py
fhdw/modelling/evaluation.py
fhdw/modelling/preprocessing.py
fhdw/modelling/pycaret.py
fhdw/modelling/tracking.py
fhdw/tests/__init__.py
fhdw/tests/conftest.py
fhdw/tests/data/automobile.csv
fhdw/tests/test_base.py
fhdw/tests/test_evaluation.py
fhdw/tests/test_preprocessing.py
fhdw/tests/test_pycaret.py
fhdw/tests/test_tracking.py
fhdw_modelling-7.3.0.dist-info/METADATA
fhdw_modelling-7.3.0.dist-info/WHEEL
fhdw_modelling-7.3.0.dist-info/RECORD
