Metadata-Version: 2.1
Name: fhdw-modelling
Version: 7.3.0
Summary: A collection of modelling tools. Intended for generic usage in FHDW projects.
Home-page: https://github.com/fhdw-forschung/modelling-tools
License: MPL-2.0
Author: Pascal Niggemeier
Author-email: pascal.niggemeier@fhdw.de
Requires-Python: >=3.11,<3.12
Classifier: License :: OSI Approved
Classifier: Programming Language :: Python :: 3
Classifier: Programming Language :: Python :: 3.11
Requires-Dist: fastapi (>=0.104.1,<0.105.0)
Requires-Dist: kaleido (==0.2.1)
Requires-Dist: mlflow (>=2.10.2,<3.0.0)
Requires-Dist: pyarrow (>=15.0.2,<16.0.0)
Requires-Dist: pycaret[mlops,models] (>=3.3.1,<4.0.0)
Requires-Dist: pyyaml (>=6.0.1,<7.0.0)
Project-URL: Bug Tracker, https://github.com/fhdw-forschung/modelling-tools/issues
Project-URL: Documentation, https://fhdw-forschung.github.io/modelling-tools/
Project-URL: Repository, https://github.com/fhdw-forschung/modelling-tools
